clandestino_minio/__init__.py
clandestino_minio/infra.py
clandestino_minio/ref.py
clandestino_minio/repository.py
clandestino_minio-0.1.1.dist-info/LICENSE
clandestino_minio-0.1.1.dist-info/METADATA
clandestino_minio-0.1.1.dist-info/WHEEL
clandestino_minio-0.1.1.dist-info/RECORD
