Metadata-Version: 2.1
Name: clandestino_minio
Version: 0.1.1
Summary: Clandestino MinIO implementation
Author: XimitGaia
Author-email: im.ximit@gmail.com
Requires-Python: >=3.11,<4.0
Classifier: Programming Language :: Python :: 3
Classifier: Programming Language :: Python :: 3.11
Classifier: Programming Language :: Python :: 3.12
Requires-Dist: clandestino-interfaces (>=0.1.0,<0.2.0)
Requires-Dist: miniopy-async (>=1.20.1,<2.0.0)
Requires-Dist: python-decouple (>=3.8,<4.0)
